ocrd_cor_asv_ann/__init__.py
ocrd_cor_asv_ann/lib/__init__.py
ocrd_cor_asv_ann/lib/alignment.py
ocrd_cor_asv_ann/lib/attention.py
ocrd_cor_asv_ann/lib/callbacks.py
ocrd_cor_asv_ann/lib/keras_train.py
ocrd_cor_asv_ann/lib/seq2seq.py
ocrd_cor_asv_ann/scripts/__init__.py
ocrd_cor_asv_ann/scripts/compare.py
ocrd_cor_asv_ann/scripts/eval.py
ocrd_cor_asv_ann/scripts/proc.py
ocrd_cor_asv_ann/scripts/repl.py
ocrd_cor_asv_ann/scripts/train.py
ocrd_cor_asv_ann/wrapper/__init__.py
ocrd_cor_asv_ann/wrapper/align.py
ocrd_cor_asv_ann/wrapper/evaluate.py
ocrd_cor_asv_ann/wrapper/join.py
ocrd_cor_asv_ann/wrapper/mark.py
ocrd_cor_asv_ann/wrapper/ocrd-tool.json
ocrd_cor_asv_ann/wrapper/transcode.py
ocrd_cor_asv_ann-0.2.0.dist-info/LICENSE
ocrd_cor_asv_ann-0.2.0.dist-info/METADATA
ocrd_cor_asv_ann-0.2.0.dist-info/WHEEL
ocrd_cor_asv_ann-0.2.0.dist-info/entry_points.txt
ocrd_cor_asv_ann-0.2.0.dist-info/top_level.txt
ocrd_cor_asv_ann-0.2.0.dist-info/RECORD
