Metadata-Version: 2.1
Name: ocrd-cor-asv-ann
Version: 0.2.0
Summary: sequence-to-sequence translator for noisy channel error correction
Author-email: Robert Sachunsky <sachunsky@informatik.uni-leipzig.de>
License: Apache-2.0
Project-URL: Homepage, https://github.com/ASVLeipzig/cor-asv-ann
Project-URL: Repository, https://github.com/ASVLeipzig/cor-asv-ann.git
Classifier: Development Status :: 5 - Production/Stable
Classifier: Environment :: Console
Classifier: Intended Audience :: Science/Research
Classifier: Intended Audience :: Other Audience
Classifier: License :: OSI Approved :: Apache Software License
Classifier: Programming Language :: Python :: 3
Classifier: Programming Language :: Python :: 3 :: Only
Classifier: Topic :: Text Processing
Requires-Python: >=3.8
License-File: LICENSE
Requires-Dist: ocrd>=3.1.1
Requires-Dist: click
Requires-Dist: keras==2.3.*
Requires-Dist: numpy
Requires-Dist: tensorflow-gpu==1.15.*
Requires-Dist: h5py<3.0.0
Requires-Dist: rapidfuzz
Requires-Dist: uniseg
Provides-Extra: plotting
Requires-Dist: matplotlib; extra == "plotting"
